Workbook

Sheet MoSCoW Analysis
A1: Library Management System – MoSCoW Prioritization
A2: Impact and Feasibility scored 1 (low) – 5 (high). Priority Score = Impact × Feasibility. Assumptions are on the 'Method & Assumptions' sheet.
A4: # | B4: Requirement | C4: Key Stakeholders | D4: Impact (1-5) | E4: Impact on Users & Stakeholders | F4: Feasibility (1-5) | G4: Feasibility (Time, Budget, Resources) | H4: Priority Score | I4: MoSCoW Category | J4: Justification | K4: Planned Release | L4: Score Band (formula)
A5: 1 | B5: Search books by title and author | C5: Students/members, librarians | D5: 5 | E5: Every user needs it on every visit; without it the catalogue is unusable and borrowing cannot happen. | F5: 5 | G5: Standard database query (SQL LIKE / full-text index); low effort, no extra cost or third-party tools. | H5: =D5*F5 -> 25 | I5: Must-Have | J5: Core function of any library system with the highest user impact and almost no delivery risk. The system fails its purpose without it. | K5: Release 1 (MVP) | L5: =IF(H5>=16,"High",IF(H5>=9,"Medium","Low")) -> High
A6: 2 | B6: Online book reservation system | C6: Members, librarians | D6: 4 | E6: Lets members hold in-demand books remotely and reduces queues and wasted visits; librarians get a clear demand view. | F6: 4 | G6: Needs a reservation table, hold queue and availability logic; moderate effort, fully achievable in-house within the timeline. | H6: =D6*F6 -> 16 | I6: Should-Have | J6: High value and feasible, but the library can operate manually (desk reservations) if it slips, so it is important but not critical for go-live. | K6: Release 1 (if time permits) / Release 2 | L6: =IF(H6>=16,"High",IF(H6>=9,"Medium","Low")) -> High
A7: 3 | B7: Monthly borrowing reports for administrators | C7: Administrators, librarians, management | D7: 4 | E7: Supports stock purchasing, policy and audit decisions; no direct effect on members' daily use. | F7: 4 | G7: Aggregation queries over existing loan data plus PDF/Excel export; moderate effort, depends on borrowing data already being captured. | H7: =D7*F7 -> 16 | I7: Should-Have | J7: Important for management, but only valuable after borrowing data accumulates; reports can be produced manually from the database initially. | K7: Release 2 | L7: =IF(H7>=16,"High",IF(H7>=9,"Medium","Low")) -> High
A8: 4 | B8: Email notifications for overdue books | C8: Members, librarians, administrators | D8: 5 | E8: Directly improves return rates, reduces lost books and manual chasing, and protects library assets. | F8: 4 | G8: Scheduled job plus SMTP/email service (free or low-cost tier); moderate effort, needs valid member emails and a due-date check. | H8: =D8*F8 -> 20 | I8: Must-Have | J8: Overdue control is a core library business rule with large operational payoff and low cost, so it belongs in the first release. | K8: Release 1 (MVP) | L8: =IF(H8>=16,"High",IF(H8>=9,"Medium","Low")) -> High
A9: 5 | B9: QR code scanning for borrowing and returning | C9: Members, librarians | D9: 3 | E9: Speeds up the checkout/return desk, but barcode, manual ID entry or typing the book ID achieves the same result. | F9: 3 | G9: Needs QR generation/labelling for every book, scanner or camera integration and a mobile-friendly UI; extra hardware and labelling effort. | H9: =D9*F9 -> 9 | I9: Could-Have | J9: A convenience improvement rather than a necessity; borrowing works without it. Add if time and budget remain after core features. | K9: Release 2 / 3 | L9: =IF(H9>=16,"High",IF(H9>=9,"Medium","Low")) -> Medium
A10: 6 | B10: User-friendly dashboard for librarians | C10: Librarians, administrators | D10: 5 | E10: Librarians use it daily to manage books, members, loans and overdue items; poor usability slows all operations. | F10: 4 | G10: Built on top of existing modules using a UI framework/templates; effort grows with the number of widgets, so keep the first version simple. | H10: =D10*F10 -> 20 | I10: Must-Have | J10: This is the main working interface of the system for staff, so a usable basic dashboard is required at launch (advanced analytics can follow later). | K10: Release 1 (basic), enhanced in Release 2 | L10: =IF(H10>=16,"High",IF(H10>=9,"Medium","Low")) -> High
A11: 7 | B11: Allow users to review and rate books | C11: Members | D11: 2 | E11: Adds engagement and helps readers choose books, but does not affect core library operations. | F11: 4 | G11: Simple review table and rating form; low effort, though moderation of inappropriate reviews adds some work. | H11: =D11*F11 -> 8 | I11: Could-Have | J11: Nice-to-have social feature with low effort but low operational impact; schedule after essential features. | K11: Release 3 | L11: =IF(H11>=16,"High",IF(H11>=9,"Medium","Low")) -> Low
A12: 8 | B12: Integrate a chatbot for user assistance | C12: Members, librarians | D12: 2 | E12: Could reduce routine enquiries, but a FAQ page and librarian help cover the need at this scale. | F12: 2 | G12: Requires NLP/AI service integration, training data, ongoing maintenance and possibly recurring API costs; high effort for the team size and budget. | H12: =D12*F12 -> 4 | I12: Won't-Have | J12: Cost and complexity are high relative to the benefit. Excluded from this release and can be reconsidered in the future once the core system is stable. | K12: Future (not this release) | L12: =IF(H12>=16,"High",IF(H12>=9,"Medium","Low")) -> Low
A13: 9 | B13: Develop a mobile app version of the system | C13: Members, librarians | D13: 4 | E13: Convenient for members, but a responsive web interface already provides mobile access. | F13: 1 | G13: Separate Android/iOS development, testing, app store accounts and maintenance; far exceeds the available time, budget and skills. | H13: =D13*F13 -> 4 | I13: Won't-Have | J13: High potential benefit, but not feasible within current constraints. A responsive web design covers mobile use for now; a native app is a future-phase candidate. | K13: Future (not this release) | L13: =IF(H13>=16,"High",IF(H13>=9,"Medium","Low")) -> Low
A14: 10 | B14: Provide multi-language support | C14: Members from diverse language backgrounds | D14: 3 | E14: Improves accessibility for non-English readers; benefit depends on the user base and is not essential for core operations. | F14: 3 | G14: Needs text externalisation (i18n) from the start and translation of all content; modest effort if planned early, costly to retrofit. | H14: =D14*F14 -> 9 | I14: Could-Have | J14: Useful for inclusivity, but the system works fully in a single language. Design the UI with i18n in mind and add languages when resources allow. | K14: Release 3 | L14: =IF(H14>=16,"High",IF(H14>=9,"Medium","Low")) -> Medium
A16: Blue numbers = scoring inputs (editable). Black = formulas.

Sheet Summary
A1: MoSCoW Summary
A3: Category | B3: No. of Requirements | C3: Avg Impact | D3: Avg Feasibility | E3: Meaning
A4: Must-Have | B4: =COUNTIF('MoSCoW Analysis'!$I$5:$I$14,A4) -> 3 | C4: =IFERROR(AVERAGEIF('MoSCoW Analysis'!$I$5:$I$14,A4,'MoSCoW Analysis'!$D$5:$D$14),0) -> 5 | D4: =IFERROR(AVERAGEIF('MoSCoW Analysis'!$I$5:$I$14,A4,'MoSCoW Analysis'!$F$5:$F$14),0) -> 4.3333333 | E4: Essential for launch; system is not viable without it.
A5: Should-Have | B5: =COUNTIF('MoSCoW Analysis'!$I$5:$I$14,A5) -> 2 | C5: =IFERROR(AVERAGEIF('MoSCoW Analysis'!$I$5:$I$14,A5,'MoSCoW Analysis'!$D$5:$D$14),0) -> 4 | D5: =IFERROR(AVERAGEIF('MoSCoW Analysis'!$I$5:$I$14,A5,'MoSCoW Analysis'!$F$5:$F$14),0) -> 4 | E5: Important and feasible; include if time allows, workarounds exist.
A6: Could-Have | B6: =COUNTIF('MoSCoW Analysis'!$I$5:$I$14,A6) -> 3 | C6: =IFERROR(AVERAGEIF('MoSCoW Analysis'!$I$5:$I$14,A6,'MoSCoW Analysis'!$D$5:$D$14),0) -> 2.6666667 | D6: =IFERROR(AVERAGEIF('MoSCoW Analysis'!$I$5:$I$14,A6,'MoSCoW Analysis'!$F$5:$F$14),0) -> 3.3333333 | E6: Desirable extras with smaller impact; first to drop if time or budget is tight.
A7: Won't-Have | B7: =COUNTIF('MoSCoW Analysis'!$I$5:$I$14,A7) -> 2 | C7: =IFERROR(AVERAGEIF('MoSCoW Analysis'!$I$5:$I$14,A7,'MoSCoW Analysis'!$D$5:$D$14),0) -> 3 | D7: =IFERROR(AVERAGEIF('MoSCoW Analysis'!$I$5:$I$14,A7,'MoSCoW Analysis'!$F$5:$F$14),0) -> 1.5 | E7: Agreed to be out of scope for this release; may be revisited later.
A8: Total | B8: =SUM(B4:B7) -> 10

Sheet Method & Assumptions
A1: Method & Assumptions
A3: MoSCoW categories
A4: Must-Have | B4: Critical for the first release; the system is unusable or non-compliant without it.
A5: Should-Have | B5: Important, high value, but a workaround exists; included if time permits.
A6: Could-Have | B6: Desirable but low impact; included only if time and budget remain.
A7: Won't-Have | B7: Not planned for this release (agreed scope exclusion), may be revisited later.
A9: Scoring criteria
A10: Impact (1-5) | B10: 5 = used by all users/staff daily or essential to core operations; 1 = affects very few users or is cosmetic.
A11: Feasibility (1-5) | B11: 5 = simple, low cost, within team skills; 1 = needs new skills, hardware, recurring cost or far exceeds the timeline.
A12: Priority Score | B12: Impact × Feasibility (max 25). Guide: ≥20 usually Must/Should; 9-16 Could; low feasibility or low score = Won't. Final category also uses judgment on whether the system can function without the feature.
A14: Assumptions (project constraints)
A15: Team and time | B15: Small team (student project scale) with roughly one academic semester to deliver.
A16: Budget | B16: Minimal/no budget: free or low-cost tools only (no paid AI APIs, no app-store fees).
A17: Users | B17: Library members (students/readers), librarians, and administrators.
A18: Platform | B18: A responsive web application is the baseline; mobile access is provided through the browser.
A19: Scores | B19: All scores are the author's estimates under these assumptions and can be edited in the 'MoSCoW Analysis' sheet.
